{
  "generated_at": "2026-04-28T04:06:22.837121+00:00",
  "articles": [
    {
      "category": "AI・テクノロジー",
      "source": "ITmedia NEWS",
      "title": "「個室の洗浄トイレ」リアルに再現、付録つきムック発売　流水音も鳴る",
      "url": "https://www.itmedia.co.jp/news/articles/2604/28/news084.html",
      "summary": "流水音や乾燥音、ノズルから水が出る音をリアルな効果音を搭載。個室を再現したペーパークラフト付き。",
      "published": "2026/04/28 12:45",
      "image_url": ""
    },
    {
      "category": "AI・テクノロジー",
      "source": "ITmedia NEWS",
      "title": "GitHub Copilot、6月1日より従量課金モデルへ移行　AIの“追い課金”時代の到来か",
      "url": "https://www.itmedia.co.jp/news/articles/2604/28/news080.html",
      "summary": "米GitHubは4月27日（現地時間）、AIコーディング支援ツール「GitHub Copilot」の全プランについて、6月1日から従量課金モデルへ移行すると発表した。",
      "published": "2026/04/28 12:40",
      "image_url": ""
    },
    {
      "category": "AI・テクノロジー",
      "source": "ITmedia NEWS",
      "title": "はてな株、2日ぶりに売買成立　一時、年初来安値も反発　荒い値動きに",
      "url": "https://www.itmedia.co.jp/news/articles/2604/28/news078.html",
      "summary": "寄り付き直後に850円まで下落し年初来安値を更新したが、その後は買い戻しが入り、午前の取引を946円で終えた。",
      "published": "2026/04/28 12:06",
      "image_url": ""
    },
    {
      "category": "AI・テクノロジー",
      "source": "ITmedia NEWS",
      "title": "アルプスアルパイン、VPN経由で不正アクセス被害　従業員の個人情報流出か",
      "url": "https://www.itmedia.co.jp/news/articles/2604/28/news075.html",
      "summary": "外部から閲覧された可能性のある情報は、同社とグループ会社の役員、従業員（退職者含む）、委託先企業の一部従業員のログインID（社員番号を一部含む）、氏名、会社メールアドレス、役職、部門名、システムID。",
      "published": "2026/04/28 11:47",
      "image_url": ""
    },
    {
      "category": "AI・テクノロジー",
      "source": "ITmedia NEWS",
      "title": "船便遅延でエレコムのマウス発売延期　「士郎正宗デザイン」復刻版",
      "url": "https://www.itmedia.co.jp/news/articles/2604/28/news067.html",
      "summary": "5月1日に発売を予定していた「士郎正宗 復刻デザインマウス」の発売日を5月下旬に延期する。",
      "published": "2026/04/28 11:05",
      "image_url": ""
    },
    {
      "category": "政治・国際情勢",
      "source": "BBC Japan",
      "title": "トランプ大統領暗殺未遂罪で容疑者を起訴　米記者会夕食会の発砲事件",
      "url": "https://www.bbc.com/japanese/articles/cp8pn3wr381o?at_medium=RSS&at_campaign=rss",
      "summary": "アメリカのトランプ大統領が出席していたホワイトハウス記者協会主催の夕食会の会場付近で発砲があった事件で、逮捕されたカリフォルニア州の男性容疑者が27日、大統領に対する暗殺未遂の罪で起訴された。この事件を受け、ホワイトハウスは警備体制の見直しを進めている。",
      "published": "2026/04/28 11:51",
      "image_url": "https://ichef.bbci.co.uk/ace/ws/240/cpsprodpb/f5bb/live/832f9740-42a4-11f1-b55d-0f258dce1735.jpg"
    },
    {
      "category": "政治・国際情勢",
      "source": "BBC Japan",
      "title": "イギリス国王夫妻、訪米開始　国王は議会演説で「民主主義の価値」守る意義を強調へ",
      "url": "https://www.bbc.com/japanese/articles/cwy25469e8eo?at_medium=RSS&at_campaign=rss",
      "summary": "イギリス国王チャールズ3世とカミラ王妃は27日、アメリカに到着した。4日間の公式訪問が始まった。イギリス君主がアメリカを公式に訪れるのは、エリザベス2世が2007年に訪れて以来。国王は連邦議会で演説し、「民主主義の価値」を守る意義を強調するほか、このところ緊張が続く英米関係の「和解と再生」を呼びかける見通し。",
      "published": "2026/04/28 12:02",
      "image_url": "https://ichef.bbci.co.uk/ace/ws/240/cpsprodpb/51f1/live/48acfb60-42a1-11f1-9fd2-ddbb69a43a23.jpg"
    },
    {
      "category": "政治・国際情勢",
      "source": "BBC Japan",
      "title": "マラソンで2時間の壁を破る　優勝のサウェ選手と2位のケジェルチャ選手、ロンドンで",
      "url": "https://www.bbc.com/japanese/articles/czd7d7956g4o?at_medium=RSS&at_campaign=rss",
      "summary": "26日にあったロンドン・マラソンの男子のレースで、セバスチャン・サウェ選手（31、ケニア）がマラソンの公式レース史上初めて、2時間を切って完走し優勝した。2位のヨミフ・ケジェルチャ選手（エチオピア）も、初マラソンで2時間を切る快挙を果たした。",
      "published": "2026/04/27 16:49",
      "image_url": "https://ichef.bbci.co.uk/ace/ws/240/cpsprodpb/800c/live/2e048080-4206-11f1-ac78-2112837ce2aa.jpg"
    },
    {
      "category": "政治・国際情勢",
      "source": "BBC Japan",
      "title": "イスラエルが空爆で14人殺害とレバノン当局、互いに停戦違反を非難",
      "url": "https://www.bbc.com/japanese/articles/cdxdxjp5w80o?at_medium=RSS&at_campaign=rss",
      "summary": "レバノン保健省は、26日のイスラエルの攻撃により、子ども2人と女性2人を含む14人が殺害され、37人が負傷したと発表した。一方のイスラエル軍は、レバノンのイスラム教シーア派組織ヒズボラのドローン攻撃により、19歳の兵士1人が殺害され、6人が負傷した述べた。停戦が発効して以降、イスラエルとヒズボラの双方が攻撃があったと報告し、相手側が合意に違反していると非難している。",
      "published": "2026/04/27 13:20",
      "image_url": "https://ichef.bbci.co.uk/ace/ws/240/cpsprodpb/0b7e/live/19c42640-41b4-11f1-9742-e92aadbab0a2.jpg"
    },
    {
      "category": "政治・国際情勢",
      "source": "BBC Japan",
      "title": "ホワイトハウス記者会夕食会の最中に発砲事件、現場の様子は",
      "url": "https://www.bbc.com/japanese/articles/c1d9d656enxo?at_medium=RSS&at_campaign=rss",
      "summary": "アメリカのトランプ大統領が出席していたホワイトハウス記者協会主催の夕食会の会場付近で発砲があった事件で、司法省のブランチ長官代行は26日、逮捕された容疑者がトランプ氏や側近らを標的としていた「可能性が高い」と述べた。トランプ氏は銃声が聞こえた直後、シークレットサービス（大統領警護隊）に促されて避難した。",
      "published": "2026/04/27 15:39",
      "image_url": "https://ichef.bbci.co.uk/ace/ws/240/cpsprodpb/c223/live/c8629b30-4184-11f1-b55d-0f258dce1735.jpg"
    },
    {
      "category": "経済・金融",
      "source": "東洋経済オンライン",
      "title": "なんとコンビニの約3倍! 卑弥呼の死後《16万基もの古墳》を日本列島に生み出した｢王の使命｣と｢庶民の誇り｣ | キャリア・教育 | 東洋経済オンライン",
      "url": "https://toyokeizai.net/articles/-/941995?utm_source=rss&utm_medium=http&utm_campaign=link_back",
      "summary": "古墳時代は､王権と地方勢力の連合を象徴する前方後円墳の拡大とともに日本列島全体へ広がりました。征服ではなく､ゆるやかな政治･経済･宗教の統合が各地に16万基もの古墳を生み出しました。なぜ人々はこれほ…",
      "published": "2026/04/28 13:00",
      "image_url": "https://tk.ismcdn.jp/mwimgs/8/7/1200w/img_87c58b5b3ff5f58aa9ea4d4616bff5451027734.jpg?nextgen=false"
    },
    {
      "category": "経済・金融",
      "source": "東洋経済オンライン",
      "title": "Pixel 10aの弱点は設定で補える　画面･動作･認証の不満を解消する実践テクニック | ビジネス | 東洋経済オンライン",
      "url": "https://toyokeizai.net/articles/-/942559?utm_source=rss&utm_medium=http&utm_campaign=link_back",
      "summary": "高性能と手ごろな価格で人気のPixel aシリーズ。その最新モデル｢Pixel 10a｣は､日本限定カラーや上位モデル譲りの性能を備えつつ､弱点も存在します。しかし設定次第で弱点を大きく補うことが可…",
      "published": "2026/04/28 12:30",
      "image_url": "https://tk.ismcdn.jp/mwimgs/1/b/1200w/img_1b8f9bc7995c2f321dcab2878b21e99e316712.jpg?nextgen=false"
    },
    {
      "category": "経済・金融",
      "source": "東洋経済オンライン",
      "title": "ちょっとした雑談で相手を不機嫌にさせる人の｢落とし穴｣　職場という危険地帯を平穏に生き抜くための武器とは何か | キャリア・教育 | 東洋経済オンライン",
      "url": "https://toyokeizai.net/articles/-/942508?utm_source=rss&utm_medium=http&utm_campaign=link_back",
      "summary": "職場の人間関係には思わぬ｢落とし穴｣が潜み､悪気のない一言がキャリアに長期的な影響を及ぼすことも。そんな危険を回避する鍵は､実は雑談や飲み会から得られる社内情報です。職場の同僚と､どう適切な距離感を…",
      "published": "2026/04/28 12:00",
      "image_url": "https://tk.ismcdn.jp/mwimgs/1/5/1200w/img_157f20330a6c0c29084a210c2da8870a190305.jpg?nextgen=false"
    },
    {
      "category": "経済・金融",
      "source": "東洋経済オンライン",
      "title": "｢静かな退職｣を決めた人がハマる人生の落とし穴……｟やる気なし｠になってしまったのはワケがある？ | キャリア・教育 | 東洋経済オンライン",
      "url": "https://toyokeizai.net/articles/-/941595?utm_source=rss&utm_medium=http&utm_campaign=link_back",
      "summary": "近年､やりがいや昇進を求めず､最低限だけ働く｢静かな退職者｣が職場で増えています。しかしその内面には｢頑張りたいけれど方法が分からない｣という葛藤が潜んでいることも。静かな退職がもたらす影響や､周囲…",
      "published": "2026/04/28 11:30",
      "image_url": "https://tk.ismcdn.jp/mwimgs/2/f/1200w/img_2f9c409add90a2db7b8f7a693edac284227500.jpg?nextgen=false"
    },
    {
      "category": "経済・金融",
      "source": "東洋経済オンライン",
      "title": "日経平均株価､最高値更新後に反落､半導体･AI関連中心に下げが広がる､日銀の金融政策決定会合を前に手控えムード | 政治・経済・投資 | 東洋経済オンライン",
      "url": "https://toyokeizai.net/articles/-/942910?utm_source=rss&utm_medium=http&utm_campaign=link_back",
      "summary": "日経平均が最高値更新後に反落し､半導体･AI関連株を中心に下げが広がる日本市場。海外要因や原油高が重なる中､日銀会合の金融政策や為替動向も注目されています。投資家心理は揺れる今､マーケットはどこへ向…",
      "published": "2026/04/28 11:11",
      "image_url": "https://tk.ismcdn.jp/mwimgs/7/d/1200w/img_7d9fc412fd03ece5463ee0069e5e1688817143.jpg?nextgen=false"
    }
  ]
}